crabpy/__init__.py
crabpy/client.py
crabpy/wsa.py
crabpy/wsse.py
crabpy/data/deelgemeenten.json
crabpy/data/gemeenten.json
crabpy/data/gewesten.json
crabpy/data/provincies.json
crabpy/data/update_data.py
crabpy/gateway/__init__.py
crabpy/gateway/adressenregister.py
crabpy/gateway/capakey.py
crabpy/gateway/crab.py
crabpy/gateway/exception.py
crabpy-1.7.0.dist-info/METADATA
crabpy-1.7.0.dist-info/WHEEL
crabpy-1.7.0.dist-info/entry_points.txt
crabpy-1.7.0.dist-info/licenses/LICENSE
crabpy-1.7.0.dist-info/RECORD
