Metadata-Version: 2.1
Name: crabpy
Version: 1.7.0
Summary: Interact with geographical webservices by Informatie Vlaanderen.
Project-URL: Repository, https://github.com/OnroerendErfgoed/crabpy.git
Project-URL: Issues, https://github.com/OnroerendErfgoed/crabpy/issues
Project-URL: Changelog, https://github.com/OnroerendErfgoed/crabpy/blob/master/CHANGES.rst
Author-email: Flanders Heritage Agency <ict@onroerenderfgoed.be>
License: The MIT License (MIT)
License-File: LICENSE
Keywords: AGIV,CAPAKEY,crabpy,pyramid,web,wsgi
Classifier: Development Status :: 5 - Production/Stable
Classifier: Intended Audience :: Developers
Classifier: License :: OSI Approved :: MIT License
Classifier: Natural Language :: English
Classifier: Operating System :: OS Independent
Classifier: Programming Language :: Python
Classifier: Programming Language :: Python :: 3.10
Classifier: Programming Language :: Python :: 3.11
Classifier: Programming Language :: Python :: 3.12
Requires-Python: <3.13,>=3.10
Requires-Dist: dogpile-cache
Requires-Dist: requests
Requires-Dist: suds-py3>=1.4.4.1
Provides-Extra: dev
Requires-Dist: black==24.10.0; extra == 'dev'
Requires-Dist: coveralls==4.0.1; extra == 'dev'
Requires-Dist: flake8-bugbear==24.8.19; extra == 'dev'
Requires-Dist: flake8-import-order==0.18.2; extra == 'dev'
Requires-Dist: flake8==7.1.1; extra == 'dev'
Requires-Dist: pre-commit==4.0.1; extra == 'dev'
Requires-Dist: pytest==8.3.3; extra == 'dev'
Requires-Dist: responses==0.25.3; extra == 'dev'
Requires-Dist: uv==0.4.20; extra == 'dev'
